sim/configured_segment_pkg_tb.vhd
-- Code your testbench here
library IEEE;
use IEEE.std_logic_1164.all;

library std;
use std.env.all;
use std.textio.all;

library work;

use work.configured_segment_pkg.all;

-- todo: create a simple design and drive DUT

entity segment_pkg_tb is
end entity;

architecture testbench of segment_pkg_tb is

    constant test_data : sentence_type(1 to 8) := (
        "AA  11  ",
        "AAAA    ",
        "AA  A   ",
        "A   AA  ",
        "A   1   ",
        "A   1111",
        "1111A   ",
        "11111111"
    );

    signal message : std_logic_vector(ENCODING_BITWIDTH'range) := (others=>'0');

begin

	process begin
        wait for 10 ns;

        for i in test_data'range loop
            message <= set_message(test_data(i));
            wait for 10 ns;
        end loop;

        finish;
    end process;

end architecture;

out/segment_pkg_tb.vcd
$date
  Tue Aug 22 22:22:10 2023
$end
$version
  GHDL v0
$end
$timescale
  1 fs
$end
$scope module standard $end
$upscope $end
$scope module textio $end
$upscope $end
$scope module std_logic_1164 $end
$upscope $end
$scope module env $end
$upscope $end
$scope module segment_pkg_tb $end
$var reg 56 ! message[55:0] $end
$upscope $end
$enddefinitions $end
#0
b00000000000000000000000000000000000000000000000000000000 !
#10000000
b00010100001010000000000000000000001000000100000000000000 !
#20000000
b00010100001010000101000010100000000000000000000000000000 !
#30000000
b00010100001010000000000000000001010000000000000000000000 !
#40000000
b00010100000000000000000000000001010000101000000000000000 !
#50000000
b00010100000000000000000000000000001000000000000000000000 !
#60000000
b00010100000000000000000000000000001000000100000010000001 !
#70000000
b00000010000001000000100000010001010000000000000000000000 !
#80000000
b00000010000001000000100000010000001000000100000010000001 !
